setup.cfg
setup.py
pytoradex/__init__.py
pytoradex/hidsensor.py
pytoradex/toradex.py
pytoradex.egg-info/PKG-INFO
pytoradex.egg-info/SOURCES.txt
pytoradex.egg-info/dependency_links.txt
pytoradex.egg-info/entry_points.txt
pytoradex.egg-info/not-zip-safe
pytoradex.egg-info/requires.txt
pytoradex.egg-info/top_level.txt