Metadata-Version: 1.0
Name: pytoradex
Version: 0.1release
Summary: Python wrappers to the Oak series of sensors sold by Toradex
Home-page: http://snim2.org
Author: Sarah Mount
Author-email: s.mount@wlv.ac.uk
License: GPL2
Keywords: sensor toradex oak
Platform: UNKNOWN
Classifier: Topic :: System :: Hardware :: Hardware Drivers
Classifier: Topic :: Software Development :: Libraries :: Python Modules
Classifier: Topic :: Software Development :: Embedded Systems
